setup.py
abDB/__init__.py
abDB.egg-info/PKG-INFO
abDB.egg-info/SOURCES.txt
abDB.egg-info/dependency_links.txt
abDB.egg-info/not-zip-safe
abDB.egg-info/top_level.txt