Metadata-Version: 1.0
Name: abDB
Version: 0.1
Summary: Useful tools for creating our CS542 Database
Home-page: UNKNOWN
Author: Tom Hartvigsen
Author-email: twhartvigsen@wpi.edu
License: WPI
Platform: UNKNOWN
